{
	"Saving dolphines": 29,
	"Bus_in_Rock_Tunnel": 30,
	"car_over_camera": 29,
	"Kids_playing_in_leaves": 29,
	"Statue of Liberty": 25,
	"Jumps": 25,
	"St Maarten Landing": 25,
	"Eiffel Tower": 25,
	"Uncut_Evening_Flight": 29,
	"Cooking": 15,
	"Scuba": 30,
	"Excavators river crossing": 25,
	"Paintball": 23,
	"Car_railcrossing": 29,
	"Base jumping": 29,
	"Playing_on_water_slide": 29,
	"Bearpark_climbing": 25,
	"playing_ball": 30,
	"Valparaiso_Downhill": 29,
	"Air_Force_One": 25,
	"Fire Domino": 30,
	"Notre_Dame": 24,
	"paluma_jump": 29,
	"Bike Polo": 30,
	"Cockpit_Landing": 29
}
